tacs/__init__.py
tacs/config.py
tacs/tests.py
tacs-0.0.1.dist-info/LICENSE
tacs-0.0.1.dist-info/METADATA
tacs-0.0.1.dist-info/NOTICE
tacs-0.0.1.dist-info/WHEEL
tacs-0.0.1.dist-info/top_level.txt
tacs-0.0.1.dist-info/RECORD
