Metadata-Version: 2.1
Name: tacs
Version: 0.0.1
Summary: TOML yet Another Configuration System
Home-page: https://github.com/Swall0w/tacs
Author: Swall0w
Author-email: 
License: UNKNOWN
Platform: UNKNOWN
Classifier: Programming Language :: Python :: 2.7
Classifier: Programming Language :: Python :: 3
Classifier: License :: OSI Approved :: Apache Software License
Classifier: Operating System :: OS Independent
Classifier: Intended Audience :: Science/Research
Classifier: Topic :: Scientific/Engineering :: Artificial Intelligence
Requires-Dist: toml
